darkstar/__init__.py
darkstar/__main__.py
darkstar/applications.py
darkstar/templating.py
darkstar-0.1.5.dist-info/entry_points.txt
darkstar-0.1.5.dist-info/LICENSE
darkstar-0.1.5.dist-info/WHEEL
darkstar-0.1.5.dist-info/METADATA
darkstar-0.1.5.dist-info/RECORD
