Metadata-Version: 2.1
Name: darkstar
Version: 0.1.5
Summary: Dark Star
Author-email: Felix Ingram <f.ingram@gmail.com>
Requires-Python: >=3.6
Classifier: License :: OSI Approved :: Apache Software License
Requires-Dist: starlette
Requires-Dist: starlette-htmx
Requires-Dist: jinja2
Requires-Dist: click
Project-URL: Home, https://github.com/lllama/dark-star
